Metadata-Version: 2.1
Name: testflows.uexpect
Version: 1.7.230414.1210501
Summary: TestFlows - uExpect
Home-page: https://github.com/testflows/testflows-uexpect
Author: Vitaliy Zakaznikov
Author-email: vzakaznikov@testflows.com
License: Apache-2.0
Classifier: Development Status :: 2 - Pre-Alpha
Classifier: Programming Language :: Python :: 3
Classifier: License :: OSI Approved :: Apache Software License
Classifier: Operating System :: POSIX :: Linux
Requires-Python: >=3.6
Provides-Extra: dev
License-File: LICENSE
